ddb_local/__init__.py
ddb_local-0.1.3.dist-info/LICENSE
ddb_local-0.1.3.dist-info/METADATA
ddb_local-0.1.3.dist-info/WHEEL
ddb_local-0.1.3.dist-info/top_level.txt
ddb_local-0.1.3.dist-info/RECORD
