Metadata-Version: 2.1
Name: ddb-local
Version: 0.1.3
Summary: UNKNOWN
Home-page: https://github.com/wbkang/ddb_local
Author: Woongbin Kang
Author-email: pypi@wbk.one
License: MIT
Platform: UNKNOWN
License-File: LICENSE
Requires-Dist: requests
